Metadata-Version: 2.1
Name: svgsynoptic2
Version: 4.3.0
Summary: Widget for displaying a SVG synoptic.
Author-email: Johan Forsberg <kits-sw@maxiv.lu.se>
License: GNU LESSER GENERAL PUBLIC LICENSE
Project-URL: Source, https://gitlab.com/MaxIV/lib-maxiv-svgsynoptic
Requires-Python: >=3.6
License-File: LICENSE.txt
Requires-Dist: pytango >=9.2.1
Requires-Dist: taurus >=4.5
Requires-Dist: pyqtwebengine
